enumhandler/__init__.py
enumhandler-0.2.0.dist-info/LICENSE
enumhandler-0.2.0.dist-info/METADATA
enumhandler-0.2.0.dist-info/WHEEL
enumhandler-0.2.0.dist-info/RECORD
