Metadata-Version: 2.1
Name: enumhandler
Version: 0.2.0
Summary: A class that allows the definition of handlers for an enum class, along withdefinition-time type and exhaustivity checks.
Author: asthasr
Author-email: 466533+asthasr@users.noreply.github.com
Requires-Python: >=3.8
Classifier: Programming Language :: Python :: 3
Classifier: Programming Language :: Python :: 3.8
Classifier: Programming Language :: Python :: 3.9
Classifier: Programming Language :: Python :: 3.10
Classifier: Programming Language :: Python :: 3.11
